[
    {
        "content": "wkwkw galagi deh makannya gabeneerrrr. mungkin makanan yg bkin aku salah makan(?) gaakan aku makan lagi smpe kpnpun walaupun enak dan pedas\ud83d\ude29 yubisayu. km jg hrs teratur ya dan makan makanan yg sehat2 ajah ok?!",
        "timestamp": "2024-01-11T04:40:06.560000+00:00",
        "url": null,
        "media_type": "text"
    },
    {
        "content": "mungkin krn makan gateratur juga yaa. jd perutnya kena. huee?? aneh bgt rasanya aku yg selalu melihat makanan semangat, harus makan atau nyemil terus, ini lihat makanan malah \ud83e\udd22\ud83e\udd22",
        "timestamp": "2024-01-11T04:40:06.035000+00:00",
        "url": null,
        "media_type": "text"
    },
    {
        "content": "harini aku lgsg lanjut kegiatan lg sampe besokbesokbesok. tapi lg kurang enak badan karena salah makan. Hahahah\ud83e\udd13 baru pertamakali kaya begini. uring uringan bgt\ud83d\ude0c",
        "timestamp": "2024-01-11T04:40:05.565000+00:00",
        "url": null,
        "media_type": "text"
    },
    {
        "content": "seru bgt kemarin premiere Ancika di Bandung, promo di Bandung, terus di jakarta juga gala premiere. Asik skali. Makasi buat apresiasinya yaaaa semoga km sukak filmnyaa",
        "timestamp": "2024-01-11T04:40:05.072000+00:00",
        "url": null,
        "media_type": "text"
    },
    {
        "content": "Aku dari Bandung tanggal 7-skrg tgl 11 belum pulang2 kerumah! Hahahah",
        "timestamp": "2024-01-11T04:40:04.525000+00:00",
        "url": null,
        "media_type": "text"
    },
    {
        "content": "Hi! How\u2019s ur day?",
        "timestamp": "2024-01-11T04:40:03.913000+00:00",
        "url": null,
        "media_type": "text"
    },
    {
        "content": "Lg ujan btw",
        "timestamp": "2024-01-04T14:20:10.885000+00:00",
        "url": null,
        "media_type": "text"
    },
    {
        "content": "Bagus gak?",
        "timestamp": "2024-01-04T14:20:10.329000+00:00",
        "url": null,
        "media_type": "text"
    },
    {
        "content": "",
        "timestamp": "2024-01-04T14:20:09.813000+00:00",
        "url": "https://cdn.discordapp.com/attachments/1177001494889893909/1192472545123901440/image.png?ex=6764d459&is=676382d9&hm=acb856d04d4293d4b71b1f27b0b00b2412b37aaf13e0aec8b6959a37e58cc3e5&",
        "media_type": "unknown"
    },
    {
        "content": "trying out my n\u00fc glasses ehehe",
        "timestamp": "2024-01-04T14:20:07.050000+00:00",
        "url": null,
        "media_type": "text"
    },
    {
        "content": "",
        "timestamp": "2024-01-04T14:20:06.351000+00:00",
        "url": "https://cdn.discordapp.com/attachments/1177001494889893909/1192472530674524272/image.png?ex=6764d456&is=676382d6&hm=2cf2fa6fd63fa269dfb540e5a4150ea18ad1f1917860bc73e0381b6469b6c2a5&",
        "media_type": "unknown"
    }
]