[
    {
        "content": "Thank youu buat yg udah nungguin",
        "timestamp": "2024-02-29T18:00:07.411000+00:00",
        "url": null,
        "media_type": "text"
    },
    {
        "content": "Akuu abis nonton konser wave to earth jd gabisa cerita sekarang",
        "timestamp": "2024-02-29T18:00:06.742000+00:00",
        "url": null,
        "media_type": "text"
    },
    {
        "content": "Finally besok udah bisa PO photobook, nanti pengen deh cerita banyak\ud83e\udd79",
        "timestamp": "2024-02-29T18:00:05.954000+00:00",
        "url": null,
        "media_type": "text"
    },
    {
        "content": "Coba tebak2an kegiatan hari ini ngapain",
        "timestamp": "2024-02-28T07:20:04.902000+00:00",
        "url": null,
        "media_type": "text"
    },
    {
        "content": "Have a good day\ud83e\udef6",
        "timestamp": "2024-02-28T07:20:04.383000+00:00",
        "url": null,
        "media_type": "text"
    },
    {
        "content": "Ngapain tudei?",
        "timestamp": "2024-02-27T16:20:31.180000+00:00",
        "url": null,
        "media_type": "text"
    },
    {
        "content": "Hari ini libur, bisaa istirahat dirumah",
        "timestamp": "2024-02-27T16:20:30.726000+00:00",
        "url": null,
        "media_type": "text"
    },
    {
        "content": "Nanti aku coba make sure lagiii, tunggu updatenya di official yaww",
        "timestamp": "2024-02-26T06:29:09.784000+00:00",
        "url": null,
        "media_type": "text"
    },
    {
        "content": "Photobook sebentar lagiii, sabar yah kita lg mengusahakan yang terbaik. Mengenai updatenya smpe kmrn ketemu masih ada revisi tp minor hehehe yang penting prepare siap2 aja okay, sedikit lg\ud83d\ude09",
        "timestamp": "2024-02-26T06:29:09.265000+00:00",
        "url": null,
        "media_type": "text"
    },
    {
        "content": "Trus aku bales via tweet\ud83e\udd79 tp tibatiba kepikiran takut orang2 berasumsi ke arah lain kaya graduation dll?  Okay jd aku hapus aja HAHAHA nanti mungkin bs dijelasin ini ke X yah",
        "timestamp": "2024-02-26T06:29:08.631000+00:00",
        "url": null,
        "media_type": "text"
    },
    {
        "content": "Btw sorry hapus tweet\ud83d\ude02 aku tadi cepetw ketik excited gara2 baca mention kalian ttg photobook",
        "timestamp": "2024-02-26T06:29:07.957000+00:00",
        "url": null,
        "media_type": "text"
    },
    {
        "content": "Goodluck buat semua kegiatannyaa",
        "timestamp": "2024-02-26T06:29:07.269000+00:00",
        "url": null,
        "media_type": "text"
    },
    {
        "content": "Haiii. Semangat senin! Mulai minggu baru lagi",
        "timestamp": "2024-02-26T06:29:06.687000+00:00",
        "url": null,
        "media_type": "text"
    },
    {
        "content": "Sampaaaai bengkulu",
        "timestamp": "2024-02-23T06:20:05.479000+00:00",
        "url": null,
        "media_type": "text"
    },
    {
        "content": "Nonton?",
        "timestamp": "2024-02-23T06:20:05.046000+00:00",
        "url": null,
        "media_type": "text"
    },
    {
        "content": "Ke bengkulu tudei, pertama kali kesana ni",
        "timestamp": "2024-02-23T06:20:04.389000+00:00",
        "url": null,
        "media_type": "text"
    },
    {
        "content": "Haiii",
        "timestamp": "2024-02-23T06:20:03.847000+00:00",
        "url": null,
        "media_type": "text"
    },
    {
        "content": "\ud83c\udf89  ucapan ultah shani \ud83c\udf89\n\nHaiii kamu, ciyeee ulang tahun nih? Happy birthdayyy!\ud83c\udf82 Doanya yang terbaik, semoga apapun yang kamu inginkan bisa terkabul aamiin. Yang penting selalu bahagia dan sukses selalu. Semangat buat menjalani setiap harinya di umur yg sekarang, gaboleh gampang nyerah! Enjoy your day\u2764\ufe0f",
        "timestamp": "2024-02-22T04:39:33.591000+00:00",
        "url": null,
        "media_type": "text"
    },
    {
        "content": "Kok gabisaaa submit foto",
        "timestamp": "2024-02-21T08:40:06.297000+00:00",
        "url": null,
        "media_type": "text"
    },
    {
        "content": "Btw ingetin aku buat share2 gift disini ya\ud83d\ude02 aku suka lupa, taulhaaaa ya",
        "timestamp": "2024-02-21T08:40:05.552000+00:00",
        "url": null,
        "media_type": "text"
    },
    {
        "content": "Haiii. Tudei ada kegiatan lagi",
        "timestamp": "2024-02-21T08:40:04.282000+00:00",
        "url": null,
        "media_type": "text"
    },
    {
        "content": "Aku sukak semua",
        "timestamp": "2024-02-19T11:20:07.147000+00:00",
        "url": null,
        "media_type": "text"
    },
    {
        "content": "Sorry belakangan jarang banget upload, tapi aku pasti bawa kok semua giftnya\ud83d\ude05 thank you yaaa",
        "timestamp": "2024-02-19T11:20:06.604000+00:00",
        "url": null,
        "media_type": "text"
    },
    {
        "content": "Btw.. sepertinya mau upload gift disini aja kali yah",
        "timestamp": "2024-02-19T11:20:06.085000+00:00",
        "url": null,
        "media_type": "text"
    },
    {
        "content": "Semangaaat hari ini\ud83e\udef6",
        "timestamp": "2024-02-19T11:20:05.409000+00:00",
        "url": null,
        "media_type": "text"
    },
    {
        "content": "Jaga kesehatan ya semua! Aku belakangan kondisinya lg kurang sehat. Kayanya cuaca sih sama ada salah makan juga\ud83d\ude29 tp tenang aja ini mendingan banget, minum obat sekali dua kali juga kayanya sembuh",
        "timestamp": "2024-02-13T02:40:04.738000+00:00",
        "url": null,
        "media_type": "text"
    },
    {
        "content": "Aku tadi ada kegiatan sedikit..",
        "timestamp": "2024-02-12T17:20:04.724000+00:00",
        "url": null,
        "media_type": "text"
    },
    {
        "content": "Haiii. How\u2019s ur day? Ngapain aja hari ini\ud83d\ude01",
        "timestamp": "2024-02-12T17:20:04.122000+00:00",
        "url": null,
        "media_type": "text"
    },
    {
        "content": "",
        "timestamp": "2024-02-06T13:00:52.535000+00:00",
        "url": "https://cdn.discordapp.com/attachments/1177001460949598218/1204411391121817660/image.png?ex=673e8644&is=673d34c4&hm=fb5a0f3909cf8645a0ba68b98ffd5f051f6246b343fdbc723fc31a12770e1c22&",
        "media_type": "unknown"
    },
    {
        "content": "",
        "timestamp": "2024-02-06T13:00:49.594000+00:00",
        "url": "https://cdn.discordapp.com/attachments/1177001460949598218/1204411378807341106/image.png?ex=673e8641&is=673d34c1&hm=101c2c71ec5932032fce52770a02d7d3a34d1fa8718986a23d5c23798c43b473&",
        "media_type": "unknown"
    },
    {
        "content": "",
        "timestamp": "2024-02-06T13:00:45.707000+00:00",
        "url": "https://cdn.discordapp.com/attachments/1177001460949598218/1204411362026061874/image.png?ex=673e863d&is=673d34bd&hm=e2b80a3858e9b84ff329b4898774f74f3874bfc217e9d5a9638181347e9b4d3c&",
        "media_type": "unknown"
    },
    {
        "content": "Disini barusan hujan, tempat kamu gimana?",
        "timestamp": "2024-02-06T13:00:42.451000+00:00",
        "url": null,
        "media_type": "text"
    },
    {
        "content": "Kalo ga ada, berarti next kesana buat liburan yah hahahaha\ud83d\ude02",
        "timestamp": "2024-02-06T13:00:41.784000+00:00",
        "url": null,
        "media_type": "text"
    },
    {
        "content": "Cuman balik lagi, kayanya ini terakhir kesana sebagai member\ud83d\ude05 tapi semoga dalam kurun waktu bbrp bulan ini semoga bisa kesana lagi",
        "timestamp": "2024-02-06T13:00:41.090000+00:00",
        "url": null,
        "media_type": "text"
    },
    {
        "content": "Btw kmrn di malay seru banget. Banyak yg kenal jeketi juga ternyata yaaah. Kaya wow ini kesempatan yg bagus buat kedepannya",
        "timestamp": "2024-02-06T13:00:40.574000+00:00",
        "url": null,
        "media_type": "text"
    },
    {
        "content": "Suka kaya gt juga ga sih? Pas lagi kegiatan ga berasa capenya. Pas udah bener2 kelar semua baru berasa hahahahaa",
        "timestamp": "2024-02-06T13:00:39.877000+00:00",
        "url": null,
        "media_type": "text"
    },
    {
        "content": "Sudaaah sampe jakarta, semalem tepar untung hari ini free jd bisa istiahat smpe siang\ud83d\ude05",
        "timestamp": "2024-02-06T13:00:39.088000+00:00",
        "url": null,
        "media_type": "text"
    },
    {
        "content": "Semalem habis kegiatan, balik rumah baru final packing..",
        "timestamp": "2024-02-01T23:20:04.643000+00:00",
        "url": null,
        "media_type": "text"
    },
    {
        "content": "Seneng ke malaysia lagi, enaknya beli apa ya?",
        "timestamp": "2024-02-01T23:20:04.226000+00:00",
        "url": null,
        "media_type": "text"
    },
    {
        "content": "Haii",
        "timestamp": "2024-02-01T23:20:03.662000+00:00",
        "url": null,
        "media_type": "text"
    }
]