[
    {
        "content": "setidak nya hargai dan cintai dirimu sendiri, kalo kamu tidak menghargai dan mencintai diri mu sendiri, lalu siapa lagi?",
        "timestamp": "2024-10-31T06:17:18.211000+00:00",
        "url": null,
        "media_type": "text"
    },
    {
        "content": "apakah aku sudah melakukan yang terbaik salama ini?\n\ntapi setelah aku pikir lagi, kenapa aku berpikir seperti itu?\n\nkalo, kalo tidak ada orang yang bilang \"kamu telah melakukan yang terbaik\" kepada diriku dan aku bertanya seperti itu kepada diriku, ko aku jahat ya?",
        "timestamp": "2024-10-31T06:17:17.865000+00:00",
        "url": null,
        "media_type": "text"
    },
    {
        "content": "banyak kegagalan dan banyak keberhasilan selama dia berada di group tersebut.\n\ndan dia sangat di segani dan di hargai oleh semua orang yang berada di group tersebut\n\naku jadi bertanya balik ke diri sendiri, apakah aku selama ini sudah berjuang habis habisan?",
        "timestamp": "2024-10-31T06:17:17.319000+00:00",
        "url": null,
        "media_type": "text"
    },
    {
        "content": "tadi juga abis nonton documentary (my new idol, lately) dia sudah berada di group nya dari 2013, sampai saat ini, gak jauh dari situ aku juga masuk JKT48 dan sampai saat ini juga\n\ndi situ, aku melihat betapa berjuang nya dia untuk group nya, walaupun teman nya datang dan pergi juga.",
        "timestamp": "2024-10-31T06:17:16.890000+00:00",
        "url": null,
        "media_type": "text"
    },
    {
        "content": "lagi baca buku, kata katanya ko kaya sakit banget, kepikiran apa yang dia rasain dulu sampai bisa dia tulis dalam sebuah karya, bukan film, tapi buku yang bisa secara langsung terasa perasaannya.",
        "timestamp": "2024-10-31T06:17:16.423000+00:00",
        "url": null,
        "media_type": "text"
    },
    {
        "content": "hari ini kegiatan sama JKT!!!",
        "timestamp": "2024-10-30T15:00:32.734000+00:00",
        "url": null,
        "media_type": "text"
    },
    {
        "content": "",
        "timestamp": "2024-10-30T15:00:11.448000+00:00",
        "url": "https://cdn.discordapp.com/attachments/1177001515857227857/1301198977533870211/903.png?ex=6764ddbb&is=67638c3b&hm=614d4052b6e8bc2723172cb6e68f3e32beeaa0c50a3d25c03cfaaa7e7a6d62a9&",
        "media_type": "unknown"
    },
    {
        "content": "aku gak foto foto banyak waktu shooting laptime. masih tepar jadi waktu nya aku pakal \ud83d\ude22 buat bobo ada foto yang aku share di X aja",
        "timestamp": "2024-10-30T14:59:39.003000+00:00",
        "url": null,
        "media_type": "text"
    },
    {
        "content": "lagi apa",
        "timestamp": "2024-10-27T14:40:40.818000+00:00",
        "url": null,
        "media_type": "text"
    },
    {
        "content": "happy banget udah lama pengen, tapi selalu gak pas waktunya buat janjian sama orang nya, pulang kali ini sempet sempetin buat appointement, gak sabar kasih lihat!!",
        "timestamp": "2024-10-26T22:55:25.813000+00:00",
        "url": null,
        "media_type": "text"
    },
    {
        "content": "\ud83e\udd17\ud83e\udd17",
        "timestamp": "2024-10-22T10:41:12.877000+00:00",
        "url": null,
        "media_type": "text"
    },
    {
        "content": "hari ini gak jadi showroooom\ud83d\ude22",
        "timestamp": "2024-10-21T12:42:15.451000+00:00",
        "url": null,
        "media_type": "text"
    },
    {
        "content": "\ud83d\ude34\ud83d\ude34\ud83d\ude34",
        "timestamp": "2024-10-21T12:42:15.026000+00:00",
        "url": null,
        "media_type": "text"
    },
    {
        "content": "",
        "timestamp": "2024-10-21T12:42:14.424000+00:00",
        "url": "https://cdn.discordapp.com/attachments/1177001515857227857/1297902770837520454/29.png?ex=6764bd66&is=67636be6&hm=36cac15252da44f4ef3044d8f23459427fe5f171a09daaa6559644364d57b0d3&",
        "media_type": "unknown"
    },
    {
        "content": "hari ini aku ada schedule shooting sama QUADLIPS, kalo selesai gak terlalu malam nanti showroom ya",
        "timestamp": "2024-10-21T12:42:13.104000+00:00",
        "url": null,
        "media_type": "text"
    },
    {
        "content": "seru banget",
        "timestamp": "2024-10-21T12:42:12.687000+00:00",
        "url": null,
        "media_type": "text"
    },
    {
        "content": "eeee bisa kasih reaction?!!!",
        "timestamp": "2024-10-21T12:42:12.111000+00:00",
        "url": null,
        "media_type": "text"
    },
    {
        "content": "",
        "timestamp": "2024-10-21T12:42:11.615000+00:00",
        "url": "https://cdn.discordapp.com/attachments/1177001515857227857/1297902758816383016/872.png?ex=6764bd63&is=67636be3&hm=6278633f16fa8d1fbf4f449a6dd658f37ee334e34286895dda933d3edcedc030&",
        "media_type": "unknown"
    },
    {
        "content": "hello",
        "timestamp": "2024-10-21T12:42:10.524000+00:00",
        "url": null,
        "media_type": "text"
    },
    {
        "content": "Btw untuk saat ini aku akan labih sering aktif di IG dulu yaa!!\ud83e\udef6\ud83c\udffb",
        "timestamp": "2024-10-16T11:15:07.986000+00:00",
        "url": null,
        "media_type": "text"
    },
    {
        "content": "main skateboard juga, badan agak encok ya bun wkkw",
        "timestamp": "2024-10-16T11:15:07.538000+00:00",
        "url": null,
        "media_type": "text"
    },
    {
        "content": "Kemarin kegiatan selesai sampai pagi, terus hari ini istirhat seharian",
        "timestamp": "2024-10-16T11:15:06.990000+00:00",
        "url": null,
        "media_type": "text"
    },
    {
        "content": "mohon maaf besok VC ku di undur \nsampai ketemu di vc pemgganti ya\nmohon pengertiannya \ud83e\udef6\ud83c\udffb\ud83d\ude4f\ud83c\udffb",
        "timestamp": "2024-10-11T15:15:07.648000+00:00",
        "url": null,
        "media_type": "text"
    },
    {
        "content": "Hello selamat malam",
        "timestamp": "2024-10-11T15:15:05.864000+00:00",
        "url": null,
        "media_type": "text"
    },
    {
        "content": "pulang ke thailand setelah kegiatan JKT, besok udah mulai kegiatan sama QL lagi",
        "timestamp": "2024-10-07T13:30:07.252000+00:00",
        "url": null,
        "media_type": "text"
    },
    {
        "content": "Kemarin pengumuman tahap 1 alhamdullilah aku ada di posisi 1, walaupun masih tahap 1 tapi aku benar benar berterimakasih karna selalu mendukung aku \n\n\ndari ssk sebalum nya aku selalu berfikir apapun hasilnya aku akan terima dengan senang \n\n\nTetapi entah mengapa ssk kali ini terasa berbeda, banyak faktor yang membuat ku ingin terus maju \n\nDan membuat perjalanan ku di JKT48 menjadi \u201csempurna\u201d",
        "timestamp": "2024-10-04T11:00:06.935000+00:00",
        "url": null,
        "media_type": "text"
    },
    {
        "content": "dari kemarin pengen banget ngobrol ngobrol disini",
        "timestamp": "2024-10-04T11:00:06.416000+00:00",
        "url": null,
        "media_type": "text"
    },
    {
        "content": "Btw aku masih di indinesia karna masih ada kegiatan JKT48",
        "timestamp": "2024-10-04T11:00:05.469000+00:00",
        "url": null,
        "media_type": "text"
    },
    {
        "content": "apakabar?",
        "timestamp": "2024-10-04T11:00:04.472000+00:00",
        "url": null,
        "media_type": "text"
    }
]